dispcat/__init__.py
dispcat/cli.py
dispcat-0.1.1.dist-info/METADATA
dispcat-0.1.1.dist-info/WHEEL
dispcat-0.1.1.dist-info/entry_points.txt
dispcat-0.1.1.dist-info/RECORD
