Metadata-Version: 2.3
Name: dispcat
Version: 0.1.1
Summary: A CLI tool to display random cat images in separate windows on your screen, with optional frameless mode.
Author: Paul Chupot
Author-email: paul.chupot@edu.escp.eu
Requires-Python: >=3.10
Classifier: Programming Language :: Python :: 3
Classifier: Programming Language :: Python :: 3.10
Classifier: Programming Language :: Python :: 3.11
Classifier: Programming Language :: Python :: 3.12
Classifier: Programming Language :: Python :: 3.13
Requires-Dist: click (>=8.2.1,<9.0.0)
Requires-Dist: matplotlib (>=3.10.6,<4.0.0)
Requires-Dist: pillow (>=11.3.0,<12.0.0)
Requires-Dist: pyqt5 (>=5.15.11,<6.0.0)
Requires-Dist: requests (>=2.32.5,<3.0.0)
